pinstance/__init__.py
pinstance-0.1.0.dist-info/METADATA
pinstance-0.1.0.dist-info/WHEEL
pinstance-0.1.0.dist-info/licenses/LICENSE
pinstance-0.1.0.dist-info/RECORD
