Metadata-Version: 2.1
Name: pinstance
Version: 0.1.0
Summary: Simple singleton class and function decorators with 0 overhead
Project-URL: homepage, https://github.com/Nyite/Pinstance
Author-email: Nazarov Pavel <unyite8@gmail.com>
License: MIT
License-File: LICENSE
Keywords: decorator,singleton
Classifier: Development Status :: 4 - Beta
Classifier: Intended Audience :: Science/Research
Classifier: License :: OSI Approved :: MIT License
Classifier: Operating System :: OS Independent
Classifier: Programming Language :: Python :: 3
Classifier: Topic :: Software Development :: Libraries :: Python Modules
Requires-Python: >=3.7
